pytivity/__init__.py
pytivity/__meta__.py
pytivity/cli.py
pytivity/kactivity.py
pytivity-0.0.4.dist-info/DESCRIPTION.rst
pytivity-0.0.4.dist-info/METADATA
pytivity-0.0.4.dist-info/RECORD
pytivity-0.0.4.dist-info/WHEEL
pytivity-0.0.4.dist-info/entry_points.txt
pytivity-0.0.4.dist-info/metadata.json
pytivity-0.0.4.dist-info/top_level.txt
