Metadata-Version: 2.0
Name: pytivity
Version: 0.0.4
Summary: Pytivity is a python3 command line manager for your KDE activities.
Home-page: https://github.com/Ovvovy/pytivity
Author: Quentin Dawans <python@quentindawans.com>, 
Author-email: python@quentindawans.com
License: MIT
Keywords: kde,activity
Platform: UNKNOWN
Classifier: License :: OSI Approved :: MIT License
Classifier: Natural Language :: English
Classifier: Programming Language :: Python :: 3
Classifier: Programming Language :: Python :: 3.5
Classifier: Environment :: Console
Requires-Dist: pydbus
Requires-Dist: terminaltables
Requires-Dist: xdg
